bxmodels/__init__.py
bxmodels/bayes/__init__.py
bxmodels/bayes/gmm.py
bxmodels/bayes/markov.py
bxmodels/bayes/utils.py
bxmodels/graph/__init__.py
bxmodels/graph/gcn.py
bxmodels/graph/utils.py
BxModels-0.4.0.dist-info/LICENSE
BxModels-0.4.0.dist-info/METADATA
BxModels-0.4.0.dist-info/WHEEL
BxModels-0.4.0.dist-info/top_level.txt
BxModels-0.4.0.dist-info/RECORD
