Metadata-Version: 2.1
Name: BxModels
Version: 0.4.0
Summary: Popular Machine Learning Models in PyTorch with Strong GPU Acceleration.
Home-page: https://gitlab.lrz.de/borchero/bxmodels
Author: Oliver Borchert
Author-email: borchero@icloud.com
License: License :: OSI Approved :: MIT License
Platform: UNKNOWN
Classifier: Development Status :: 4 - Beta
Classifier: Programming Language :: Python :: 3.7
Classifier: Topic :: Software Development :: Libraries
Requires-Python: >=3.7
Requires-Dist: torch (<1.4.0,>=1.3.1)
Requires-Dist: numpy (<2.0.0,>=1.18.1)
Requires-Dist: bxtorch (<0.8.0,>=0.7.0)
